odoo/addons/stock_picking_product_kit_helper/README.rst
odoo/addons/stock_picking_product_kit_helper/__init__.py
odoo/addons/stock_picking_product_kit_helper/__manifest__.py
odoo/addons/stock_picking_product_kit_helper/i18n/it.po
odoo/addons/stock_picking_product_kit_helper/i18n/stock_picking_product_kit_helper.pot
odoo/addons/stock_picking_product_kit_helper/models/__init__.py
odoo/addons/stock_picking_product_kit_helper/models/stock_picking.py
odoo/addons/stock_picking_product_kit_helper/readme/CONTRIBUTORS.rst
odoo/addons/stock_picking_product_kit_helper/readme/DESCRIPTION.rst
odoo/addons/stock_picking_product_kit_helper/readme/HISTORY.rst
odoo/addons/stock_picking_product_kit_helper/readme/USAGE.rst
odoo/addons/stock_picking_product_kit_helper/security/ir.model.access.csv
odoo/addons/stock_picking_product_kit_helper/static/description/icon.png
odoo/addons/stock_picking_product_kit_helper/static/description/icon.svg
odoo/addons/stock_picking_product_kit_helper/static/description/index.html
odoo/addons/stock_picking_product_kit_helper/tests/__init__.py
odoo/addons/stock_picking_product_kit_helper/tests/test_stock_picking_product_kit_helper.py
odoo/addons/stock_picking_product_kit_helper/views/stock_view.xml
odoo_addon_stock_picking_product_kit_helper-15.0.0.1.0.5.dist-info/METADATA
odoo_addon_stock_picking_product_kit_helper-15.0.0.1.0.5.dist-info/WHEEL
odoo_addon_stock_picking_product_kit_helper-15.0.0.1.0.5.dist-info/top_level.txt
odoo_addon_stock_picking_product_kit_helper-15.0.0.1.0.5.dist-info/RECORD
