Metadata-Version: 2.1
Name: odoo-addon-stock-picking-product-kit-helper
Version: 15.0.0.1.0.5
Summary: Set quanity in picking line based on product kit quantity
Home-page: https://github.com/OCA/manufacture
Author: Ecosoft, Odoo Community Association (OCA)
Author-email: support@odoo-community.org
License: AGPL-3
Platform: UNKNOWN
Classifier: Programming Language :: Python
Classifier: Framework :: Odoo
Classifier: Framework :: Odoo :: 15.0
Classifier: License :: OSI Approved :: GNU Affero General Public License v3
Requires-Python: >=3.8
Requires-Dist: odoo <15.1dev,>=15.0a
